pypricingchain/__init__.py
pypricingchain/launch_app.py
pypricingchain/phoenix.py
pypricingchain/pricer.py
pypricingchain-0.2.10.dist-info/LICENSE
pypricingchain-0.2.10.dist-info/METADATA
pypricingchain-0.2.10.dist-info/WHEEL
pypricingchain-0.2.10.dist-info/RECORD
