Metadata-Version: 2.3
Name: pypricingchain
Version: 0.2.10
Summary: Pybacktestchain was cool, but it was missing a pricing feature ...
License: MIT
Author: Louis Schiele
Requires-Python: >=3.11,<4.0
Classifier: License :: OSI Approved :: MIT License
Classifier: Programming Language :: Python :: 3
Classifier: Programming Language :: Python :: 3.11
Classifier: Programming Language :: Python :: 3.12
Classifier: Programming Language :: Python :: 3.13
Requires-Dist: matplotlib (>=3.10.0,<4.0.0)
Requires-Dist: numpy (==1.26.4)
Requires-Dist: pybacktestchain (>=0.2.1,<0.3.0)
Requires-Dist: scipy (==1.13.1)
Requires-Dist: streamlit (>=1.41.1,<2.0.0)
